aws_finops_dashboard/__init__.py
aws_finops_dashboard/aws_client.py
aws_finops_dashboard/cli.py
aws_finops_dashboard/cost_processor.py
aws_finops_dashboard/dashboard_runner.py
aws_finops_dashboard/export_handler.py
aws_finops_dashboard/helpers.py
aws_finops_dashboard/main.py
aws_finops_dashboard/pdf_utils.py
aws_finops_dashboard/profile_processor.py
aws_finops_dashboard/types.py
aws_finops_dashboard/visualisations.py
aws_finops_dashboard-2.3.0.dist-info/METADATA
aws_finops_dashboard-2.3.0.dist-info/WHEEL
aws_finops_dashboard-2.3.0.dist-info/entry_points.txt
aws_finops_dashboard-2.3.0.dist-info/licenses/LICENSE
aws_finops_dashboard-2.3.0.dist-info/RECORD
