Metadata-Version: 2.4
Name: aws-finops-dashboard
Version: 2.3.0
Summary: A terminal-based AWS cost and resource dashboard.
Project-URL: Homepage, https://github.com/ravikiranvm/aws-finops-dashboard
Project-URL: Source, https://github.com/ravikiranvm/aws-finops-dashboard
Author: Ravi Kiran Vallamkonda
License: MIT
License-File: LICENSE
Keywords: aws,cli,cloud,cost,dashboard,finops
Requires-Python: >=3.8
Requires-Dist: boto3>=1.37.28
Requires-Dist: packaging>=21.0
Requires-Dist: pyyaml>=6.0.2
Requires-Dist: reportlab>=3.6.1
Requires-Dist: requests>=2.0.0
Requires-Dist: rich>=14.0.0
Requires-Dist: slack-sdk>=3.39.0
Requires-Dist: tomli>=2.2.1
Provides-Extra: dev
Requires-Dist: black>=23.0.0; extra == 'dev'
Requires-Dist: hatch>=1.9.0; extra == 'dev'
Requires-Dist: isort>=5.12.0; extra == 'dev'
Requires-Dist: mypy>=1.5.1; extra == 'dev'
Requires-Dist: types-boto3; extra == 'dev'
Requires-Dist: types-pyyaml; extra == 'dev'
Requires-Dist: types-reportlab; extra == 'dev'
Requires-Dist: types-requests; extra == 'dev'
Requires-Dist: types-toml; extra == 'dev'
